PyPardot4-1.1.5.dist-info/DESCRIPTION.rst
PyPardot4-1.1.5.dist-info/METADATA
PyPardot4-1.1.5.dist-info/RECORD
PyPardot4-1.1.5.dist-info/WHEEL
PyPardot4-1.1.5.dist-info/metadata.json
PyPardot4-1.1.5.dist-info/top_level.txt
pypardot/__init__.py
pypardot/client.py
pypardot/errors.py
pypardot/objects/__init__.py
pypardot/objects/accounts.py
pypardot/objects/campaigns.py
pypardot/objects/customfields.py
pypardot/objects/customredirects.py
pypardot/objects/dynamiccontent.py
pypardot/objects/emailclicks.py
pypardot/objects/emails.py
pypardot/objects/emailtemplates.py
pypardot/objects/forms.py
pypardot/objects/lifecyclehistories.py
pypardot/objects/lifecyclestages.py
pypardot/objects/listmemberships.py
pypardot/objects/lists.py
pypardot/objects/opportunities.py
pypardot/objects/prospectaccounts.py
pypardot/objects/prospects.py
pypardot/objects/tagobjects.py
pypardot/objects/tags.py
pypardot/objects/users.py
pypardot/objects/visitoractivities.py
pypardot/objects/visitors.py
pypardot/objects/visits.py
